Maquina/probador.v
module probador#(parameter BITBUS =1)
		(input idle_out, active_out, error_out, init_out,
		input idle_out_estr, active_out_estr, error_out_estr, init_out_estr,
		input [BITBUS-1:0] umbralMF_out, umbralVC_out, umbralD_out,
		input [BITBUS-1:0] umbralMF_out_estr, umbralVC_out_estr, umbralD_out_estr,
		output reg clk,
		output reg reset,
		output reg [4:0] Fifo_empties, Fifo_errors,
		output reg  [BITBUS - 1:0] umbralMF, umbralVC, umbralD);
		
	initial begin
		$dumpfile("resultados.vcd");
		$dumpvars;
		
		reset<=0;
		umbralMF<=0;
		umbralVC<=0;
		umbralD<=0;
		Fifo_empties <=5'b11111;
		Fifo_errors <=00000;
		
		@(posedge clk);
		//@(posedge clk);
		reset<=1;
		@(posedge clk);
		//@(posedge clk);
		umbralMF<=1;
		umbralVC<=1;
		umbralD<=1;
		 //Este cambio a 0 funciona, aqui se prende init_out
		@(posedge clk);
		Fifo_empties <=5'b11111;
		@(posedge clk);
		Fifo_empties <= 11001; //Hay dos fifos que no estan vacios. Se deberia cambiar de estado a ACTIVE
		@(posedge clk); //Se deberia estar en ACTIVE
		Fifo_empties <=10001; //Hay otro FIFO que ya no esta vacio
		//No deberian haber errores
		@(posedge clk); //Aqui cambie las senales de  0 y 0 a 1 y 1
		Fifo_errors<=00001; //Se detecto un error, se deberia pasar ahora a ERROR
		@(posedge clk);
		//Se deberia mantener en error por un ciclo mas
		@(posedge clk); //Deactivamos el error para intentar saltar a RESET
		Fifo_errors<=00000;
		@(posedge clk);
		
		@(posedge clk);
		$finish;
		
		
	end		
	
	
	
initial clk <=0;
always #4 clk <= ~clk;
endmodule

Maquina/maquina_synth.v
/* Generated by Yosys 0.9 (git sha1 1979e0b) */

(* dynports =  1  *)
(* top =  1  *)
(* src = "maquina.v:1" *)
module maquina_synth(clk, reset, umbralMF, umbralVC, umbralD, Fifo_empties, Fifo_errors, init_out, idle_out, active_out, error_out, umbralMF_out, umbralVC_out, umbralD_out, state_estr, next_state_estr);
  (* src = "maquina.v:25" *)
  wire [3:0] _00_;
  wire _01_;
  wire _02_;
  wire _03_;
  wire _04_;
  wire _05_;
  wire _06_;
  wire _07_;
  wire _08_;
  wire _09_;
  wire _10_;
  wire _11_;
  wire _12_;
  wire _13_;
  wire _14_;
  wire _15_;
  wire _16_;
  wire _17_;
  wire _18_;
  wire _19_;
  wire _20_;
  wire _21_;
  wire _22_;
  wire _23_;
  wire _24_;
  wire _25_;
  wire _26_;
  wire _27_;
  wire _28_;
  wire _29_;
  wire _30_;
  wire _31_;
  wire _32_;
  wire _33_;
  wire _34_;
  wire _35_;
  wire _36_;
  wire _37_;
  wire _38_;
  wire _39_;
  wire _40_;
  wire _41_;
  (* src = "maquina.v:7" *)
  input [4:0] Fifo_empties;
  (* src = "maquina.v:8" *)
  input [4:0] Fifo_errors;
  (* src = "maquina.v:11" *)
  output active_out;
  (* src = "maquina.v:2" *)
  input clk;
  (* src = "maquina.v:12" *)
  output error_out;
  (* src = "maquina.v:10" *)
  output idle_out;
  (* src = "maquina.v:9" *)
  output init_out;
  (* src = "maquina.v:17" *)
  output [3:0] next_state_estr;
  (* src = "maquina.v:3" *)
  input reset;
  (* src = "maquina.v:16" *)
  output [3:0] state_estr;
  (* src = "maquina.v:6" *)
  input umbralD;
  (* src = "maquina.v:15" *)
  output umbralD_out;
  (* src = "maquina.v:4" *)
  input umbralMF;
  (* src = "maquina.v:13" *)
  output umbralMF_out;
  (* src = "maquina.v:5" *)
  input umbralVC;
  (* src = "maquina.v:14" *)
  output umbralVC_out;
  NOT _42_ (
    .A(Fifo_errors[2]),
    .Y(_01_)
  );
  NOT _43_ (
    .A(Fifo_errors[3]),
    .Y(_02_)
  );
  NOT _44_ (
    .A(state_estr[0]),
    .Y(_03_)
  );
  NOT _45_ (
    .A(state_estr[1]),
    .Y(_04_)
  );
  NOT _46_ (
    .A(state_estr[2]),
    .Y(_05_)
  );
  NOT _47_ (
    .A(umbralMF),
    .Y(_06_)
  );
  NOT _48_ (
    .A(umbralVC),
    .Y(_07_)
  );
  NOT _49_ (
    .A(umbralD),
    .Y(_08_)
  );
  NOT _50_ (
    .A(reset),
    .Y(_09_)
  );
  NOT _51_ (
    .A(Fifo_empties[0]),
    .Y(_10_)
  );
  NOR _52_ (
    .A(_03_),
    .B(state_estr[2]),
    .Y(_11_)
  );
  NAND _53_ (
    .A(state_estr[0]),
    .B(_05_),
    .Y(_12_)
  );
  NOR _54_ (
    .A(state_estr[1]),
    .B(_12_),
    .Y(_13_)
  );
  NAND _55_ (
    .A(_04_),
    .B(_11_),
    .Y(_14_)
  );
  NOR _56_ (
    .A(_08_),
    .B(_14_),
    .Y(umbralD_out)
  );
  NOR _57_ (
    .A(_07_),
    .B(_14_),
    .Y(umbralVC_out)
  );
  NOR _58_ (
    .A(_06_),
    .B(_14_),
    .Y(umbralMF_out)
  );
  NOR _59_ (
    .A(Fifo_errors[0]),
    .B(Fifo_errors[1]),
    .Y(_15_)
  );
  NAND _60_ (
    .A(_01_),
    .B(_02_),
    .Y(_16_)
  );
  NOR _61_ (
    .A(Fifo_errors[4]),
    .B(_16_),
    .Y(_17_)
  );
  NAND _62_ (
    .A(_15_),
    .B(_17_),
    .Y(_18_)
  );
  NOR _63_ (
    .A(state_estr[0]),
    .B(state_estr[1]),
    .Y(_19_)
  );
  NAND _64_ (
    .A(_03_),
    .B(_04_),
    .Y(_20_)
  );
  NAND _65_ (
    .A(state_estr[2]),
    .B(_19_),
    .Y(_21_)
  );
  NAND _66_ (
    .A(state_estr[2]),
    .B(_18_),
    .Y(_22_)
  );
  NOR _67_ (
    .A(_20_),
    .B(_22_),
    .Y(error_out)
  );
  NAND _68_ (
    .A(state_estr[1]),
    .B(_11_),
    .Y(_23_)
  );
  NOR _69_ (
    .A(_18_),
    .B(_23_),
    .Y(active_out)
  );
  NOR _70_ (
    .A(_04_),
    .B(_10_),
    .Y(_24_)
  );
  NAND _71_ (
    .A(Fifo_empties[1]),
    .B(Fifo_empties[2]),
    .Y(_25_)
  );
  NAND _72_ (
    .A(Fifo_empties[3]),
    .B(Fifo_empties[4]),
    .Y(_26_)
  );
  NOR _73_ (
    .A(_25_),
    .B(_26_),
    .Y(_27_)
  );
  NAND _74_ (
    .A(_24_),
    .B(_27_),
    .Y(_28_)
  );
  NOR _75_ (
    .A(state_estr[0]),
    .B(state_estr[2]),
    .Y(_29_)
  );
  NAND _76_ (
    .A(_03_),
    .B(_05_),
    .Y(_30_)
  );
  NOR _77_ (
    .A(_28_),
    .B(_30_),
    .Y(idle_out)
  );
  NOR _78_ (
    .A(umbralMF),
    .B(umbralVC),
    .Y(_31_)
  );
  NAND _79_ (
    .A(_08_),
    .B(_31_),
    .Y(_32_)
  );
  NAND _80_ (
    .A(_13_),
    .B(_32_),
    .Y(_33_)
  );
  NOT _81_ (
    .A(_33_),
    .Y(init_out)
  );
  NAND _82_ (
    .A(_05_),
    .B(_28_),
    .Y(_34_)
  );
  NOR _83_ (
    .A(state_estr[0]),
    .B(_34_),
    .Y(_35_)
  );
  NOR _84_ (
    .A(active_out),
    .B(_35_),
    .Y(_36_)
  );
  NOT _85_ (
    .A(_36_),
    .Y(next_state_estr[0])
  );
  NOR _86_ (
    .A(_09_),
    .B(_36_),
    .Y(_00_[0])
  );
  NAND _87_ (
    .A(state_estr[1]),
    .B(_29_),
    .Y(_37_)
  );
  NAND _88_ (
    .A(_33_),
    .B(_37_),
    .Y(_38_)
  );
  NOR _89_ (
    .A(active_out),
    .B(_38_),
    .Y(_39_)
  );
  NOT _90_ (
    .A(_39_),
    .Y(next_state_estr[1])
  );
  NOR _91_ (
    .A(_09_),
    .B(_39_),
    .Y(_00_[1])
  );
  NAND _92_ (
    .A(_21_),
    .B(_23_),
    .Y(_40_)
  );
  NAND _93_ (
    .A(_18_),
    .B(_40_),
    .Y(_41_)
  );
  NOT _94_ (
    .A(_41_),
    .Y(next_state_estr[2])
  );
  NOR _95_ (
    .A(_09_),
    .B(_41_),
    .Y(_00_[2])
  );
  (* src = "maquina.v:25" *)
  DFF _96_ (
    .C(clk),
    .D(_00_[0]),
    .Q(state_estr[0])
  );
  (* src = "maquina.v:25" *)
  DFF _97_ (
    .C(clk),
    .D(_00_[1]),
    .Q(state_estr[1])
  );
  (* src = "maquina.v:25" *)
  DFF _98_ (
    .C(clk),
    .D(_00_[2]),
    .Q(state_estr[2])
  );
  assign _00_[3] = 1'h0;
  assign next_state_estr[3] = 1'h0;
  assign state_estr[3] = 1'h0;
endmodule

Maquina/maquina.v
module maquina#(parameter BITBUS = 1)
		(input clk,
		input reset,
		input [BITBUS-1:0] umbralMF,
		input [BITBUS-1:0] umbralVC,
		input [BITBUS-1:0] umbralD,
		input [4:0] Fifo_empties,
		input [4:0] Fifo_errors,
		output reg init_out,
		output reg idle_out,
		output reg active_out,
		output reg error_out,
		output reg [BITBUS-1:0] umbralMF_out,
		output reg [BITBUS-1:0] umbralVC_out,
		output reg [BITBUS-1:0] umbralD_out,
		output reg [3:0] state, 
		output reg [3:0]next_state);

parameter RESET=0;
parameter INIT =1;
parameter IDLE =2;
parameter ACTIVE=3;
parameter ERROR=4;

 always @ (posedge clk) begin
        if(~reset) begin
            state <= RESET; 
          //  error_out <=0;
        end
        else begin
            state <= next_state;
            
        end
    end		

always @(*) begin
	idle_out=0;
	active_out=0;
	error_out=0;
	next_state=state;
	init_out = 0;
	umbralMF_out = 0;
	umbralVC_out = 0;
	umbralD_out = 0;
	case(state)
		RESET: begin
		//For RESET state
			next_state= INIT;
		end
		
		INIT: begin
		//For INIT state
			if(umbralMF || umbralVC || umbralD)begin
			//Si hay algun umbral ON, init_out se enciende
				init_out=1;
				umbralMF_out = umbralMF;
				umbralVC_out = umbralVC;
				umbralD_out = umbralD;
				next_state= IDLE;
			end else begin
			//Si ningun umbral esta on, se vuelve a RESET e init_out se queda apagado
				init_out=0;
				umbralMF_out = 0;
				umbralVC_out = 0;
				umbralD_out = 0;
				next_state= RESET;
			end
		end
		
		IDLE: begin
		//For IDLE state
			if(Fifo_empties == 5'b11111)begin 
				idle_out=1;
				next_state= IDLE;
			end else begin
				idle_out=0;
				next_state= ACTIVE;
			end 
		end
		
		ACTIVE: begin
		//For ACTIVE state
			if(Fifo_errors == 00000) begin //Si el fifo no esta ni lleno, ni vacio, osea que tiene informacion adentro que se puede transmitir
				active_out=1;
				next_state=ACTIVE;
			end else begin
			//Este caso generaria un error puesto que el fifo no puede estar vacio y lleno al mismo tiempo
				active_out=0;
				next_state=ERROR; 	
			end 
			
		end
		
		ERROR: begin
		//For ERROR state
			if(Fifo_errors != 00000)begin
				error_out=1;
				next_state=ERROR;
			end else begin
				error_out=0;
				next_state=RESET;
			end		
		end
		default: begin
			next_state= RESET;
			idle_out=0;
			active_out=0;
			error_out=0;
		end
	endcase	
end


endmodule

Maquina/BancoPruebas.v
`include "maquina.v"
`include "probador.v"
`include "cmos_cells.v"
`include "maquina_synth.v"

module BancoPruebas;

parameter BITBUS=1;

wire clk, reset;

wire [4:0] Fifo_empties, Fifo_errors;

wire [BITBUS-1:0] umbralMF, umbralVC, umbralD;

wire [BITBUS-1:0] umbralMF_out, umbralVC_out, umbralD_out;
wire [BITBUS-1:0] umbralMF_out_estr, umbralVC_out_estr, umbralD_out_estr;

wire init_out, idle_out, active_out, error_out;
wire idle_out_estr, active_out_estr, error_out_estr, init_out_estr;
wire [3:0] next_state, next_state_estr, state, state_estr;

maquina maquina(.clk	(clk),
		.reset	(reset),
		.umbralMF	(umbralMF[BITBUS-1:0]),
		.umbralVC	(umbralVC[BITBUS-1:0]),
		.umbralD	(umbralD[BITBUS-1:0]),
		.umbralMF_out	(umbralMF_out[BITBUS-1:0]),
		.umbralVC_out	(umbralVC_out[BITBUS-1:0]),
		.umbralD_out	(umbralD_out[BITBUS-1:0]),
		.Fifo_empties	(Fifo_empties[4:0]),
		.Fifo_errors	(Fifo_errors[4:0]),
		.init_out	(init_out),
		.idle_out	(idle_out),
		.active_out	(active_out),
		.error_out	(error_out),
		.state		(state[3:0]),
		.next_state (next_state[3:0]));

maquina_synth maquina_synth(.clk	(clk),
		.reset	(reset),
		.umbralMF	(umbralMF[BITBUS-1:0]),
		.umbralVC	(umbralVC[BITBUS-1:0]),
		.umbralD	(umbralD[BITBUS-1:0]),
		.umbralMF_out	(umbralMF_out_estr[BITBUS-1:0]),
		.umbralVC_out	(umbralVC_out_estr[BITBUS-1:0]),
		.umbralD_out	(umbralD_out_estr[BITBUS-1:0]),
		.Fifo_empties	(Fifo_empties[4:0]),
		.Fifo_errors	(Fifo_errors[4:0]),
		.init_out	(init_out_estr),
		.idle_out	(idle_out_estr),
		.active_out	(active_out_estr),
		.error_out	(error_out_estr),
		.state_estr		(state_estr[3:0]),
		.next_state_estr (next_state_estr[3:0]));		

probador probador(.clk	(clk),
		.reset	(reset),
		.umbralMF	(umbralMF[BITBUS-1:0]),
		.umbralVC	(umbralVC[BITBUS-1:0]),
		.umbralD	(umbralD[BITBUS-1:0]),
		.umbralMF_out	(umbralMF_out[BITBUS-1:0]),
		.umbralVC_out	(umbralVC_out[BITBUS-1:0]),
		.umbralD_out	(umbralD_out[BITBUS-1:0]),
		.Fifo_empties	(Fifo_empties[4:0]),
		.Fifo_errors	(Fifo_errors[4:0]),
		.umbralMF_out_estr	(umbralMF_out_estr[BITBUS-1:0]),
		.umbralVC_out_estr	(umbralVC_out_estr[BITBUS-1:0]),
		.umbralD_out_estr	(umbralD_out_estr[BITBUS-1:0]),
		.init_out_estr	(init_out_estr),
		.idle_out_estr	(idle_out_estr),
		.active_out_estr	(active_out_estr),
		.error_out_estr	(error_out_estr),
		.init_out	(init_out),
		.idle_out	(idle_out),
		.active_out	(active_out),
		.error_out	(error_out));

endmodule

Memoria/cmos_cells.v

module BUF(A, Y);
input A;
output Y;
assign Y = A;
endmodule

module NOT(A, Y);
input A;
output Y;
assign Y = ~A;
endmodule

module NAND(A, B, Y);
input A, B;
output Y;
assign Y = ~(A & B);
endmodule

module NOR(A, B, Y);
input A, B;
output Y;
assign Y = ~(A | B);
endmodule

module DFF(C, D, Q);
input C, D;
output reg Q;
always @(posedge C)
	Q <= D;
endmodule

module DFFSR(C, D, Q, S, R);
input C, D, S, R;
output reg Q;
always @(posedge C, posedge S, posedge R)
	if (S)
		Q <= 1'b1;
	else if (R)
		Q <= 1'b0;
	else
		Q <= D;
endmodule

Maquina/resultados.vcd
$date
	Fri Nov  6 14:28:20 2020
$end
$version
	Icarus Verilog
$end
$timescale
	1s
$end
$scope module BUF $end
$var wire 1 ! A $end
$var wire 1 " Y $end
$upscope $end
$scope module BancoPruebas $end
$var wire 1 # umbralVC_out_estr $end
$var wire 1 $ umbralVC_out $end
$var wire 1 % umbralVC $end
$var wire 1 & umbralMF_out_estr $end
$var wire 1 ' umbralMF_out $end
$var wire 1 ( umbralMF $end
$var wire 1 ) umbralD_out_estr $end
$var wire 1 * umbralD_out $end
$var wire 1 + umbralD $end
$var wire 4 , state_estr [3:0] $end
$var wire 4 - state [3:0] $end
$var wire 1 . reset $end
$var wire 4 / next_state_estr [3:0] $end
$var wire 4 0 next_state [3:0] $end
$var wire 1 1 init_out_estr $end
$var wire 1 2 init_out $end
$var wire 1 3 idle_out_estr $end
$var wire 1 4 idle_out $end
$var wire 1 5 error_out_estr $end
$var wire 1 6 error_out $end
$var wire 1 7 clk $end
$var wire 1 8 active_out_estr $end
$var wire 1 9 active_out $end
$var wire 5 : Fifo_errors [4:0] $end
$var wire 5 ; Fifo_empties [4:0] $end
$scope module maquina $end
$var wire 1 % umbralVC $end
$var wire 1 ( umbralMF $end
$var wire 1 + umbralD $end
$var wire 1 . reset $end
$var wire 1 7 clk $end
$var wire 5 < Fifo_errors [4:0] $end
$var wire 5 = Fifo_empties [4:0] $end
$var reg 1 9 active_out $end
$var reg 1 6 error_out $end
$var reg 1 4 idle_out $end
$var reg 1 2 init_out $end
$var reg 4 > next_state [3:0] $end
$var reg 4 ? state [3:0] $end
$var reg 1 * umbralD_out $end
$var reg 1 ' umbralMF_out $end
$var reg 1 $ umbralVC_out $end
$upscope $end
$scope module maquina_synth $end
$var wire 1 # umbralVC_out $end
$var wire 1 % umbralVC $end
$var wire 1 & umbralMF_out $end
$var wire 1 ( umbralMF $end
$var wire 1 ) umbralD_out $end
$var wire 1 + umbralD $end
$var wire 4 @ state_estr [3:0] $end
$var wire 1 . reset $end
$var wire 4 A next_state_estr [3:0] $end
$var wire 1 1 init_out $end
$var wire 1 3 idle_out $end
$var wire 1 5 error_out $end
$var wire 1 7 clk $end
$var wire 1 8 active_out $end
$var wire 1 B _41_ $end
$var wire 1 C _40_ $end
$var wire 1 D _39_ $end
$var wire 1 E _38_ $end
$var wire 1 F _37_ $end
$var wire 1 G _36_ $end
$var wire 1 H _35_ $end
$var wire 1 I _34_ $end
$var wire 1 J _33_ $end
$var wire 1 K _32_ $end
$var wire 1 L _31_ $end
$var wire 1 M _30_ $end
$var wire 1 N _29_ $end
$var wire 1 O _28_ $end
$var wire 1 P _27_ $end
$var wire 1 Q _26_ $end
$var wire 1 R _25_ $end
$var wire 1 S _24_ $end
$var wire 1 T _23_ $end
$var wire 1 U _22_ $end
$var wire 1 V _21_ $end
$var wire 1 W _20_ $end
$var wire 1 X _19_ $end
$var wire 1 Y _18_ $end
$var wire 1 Z _17_ $end
$var wire 1 [ _16_ $end
$var wire 1 \ _15_ $end
$var wire 1 ] _14_ $end
$var wire 1 ^ _13_ $end
$var wire 1 _ _12_ $end
$var wire 1 ` _11_ $end
$var wire 1 a _10_ $end
$var wire 1 b _09_ $end
$var wire 1 c _08_ $end
$var wire 1 d _07_ $end
$var wire 1 e _06_ $end
$var wire 1 f _05_ $end
$var wire 1 g _04_ $end
$var wire 1 h _03_ $end
$var wire 1 i _02_ $end
$var wire 1 j _01_ $end
$var wire 4 k _00_ [3:0] $end
$var wire 5 l Fifo_errors [4:0] $end
$var wire 5 m Fifo_empties [4:0] $end
$scope module _42_ $end
$var wire 1 n A $end
$var wire 1 j Y $end
$upscope $end
$scope module _43_ $end
$var wire 1 o A $end
$var wire 1 i Y $end
$upscope $end
$scope module _44_ $end
$var wire 1 p A $end
$var wire 1 h Y $end
$upscope $end
$scope module _45_ $end
$var wire 1 q A $end
$var wire 1 g Y $end
$upscope $end
$scope module _46_ $end
$var wire 1 r A $end
$var wire 1 f Y $end
$upscope $end
$scope module _47_ $end
$var wire 1 e Y $end
$var wire 1 ( A $end
$upscope $end
$scope module _48_ $end
$var wire 1 d Y $end
$var wire 1 % A $end
$upscope $end
$scope module _49_ $end
$var wire 1 c Y $end
$var wire 1 + A $end
$upscope $end
$scope module _50_ $end
$var wire 1 b Y $end
$var wire 1 . A $end
$upscope $end
$scope module _51_ $end
$var wire 1 s A $end
$var wire 1 a Y $end
$upscope $end
$scope module _52_ $end
$var wire 1 h A $end
$var wire 1 t B $end
$var wire 1 ` Y $end
$upscope $end
$scope module _53_ $end
$var wire 1 u A $end
$var wire 1 f B $end
$var wire 1 _ Y $end
$upscope $end
$scope module _54_ $end
$var wire 1 v A $end
$var wire 1 _ B $end
$var wire 1 ^ Y $end
$upscope $end
$scope module _55_ $end
$var wire 1 g A $end
$var wire 1 ` B $end
$var wire 1 ] Y $end
$upscope $end
$scope module _56_ $end
$var wire 1 c A $end
$var wire 1 ] B $end
$var wire 1 ) Y $end
$upscope $end
$scope module _57_ $end
$var wire 1 d A $end
$var wire 1 ] B $end
$var wire 1 # Y $end
$upscope $end
$scope module _58_ $end
$var wire 1 e A $end
$var wire 1 ] B $end
$var wire 1 & Y $end
$upscope $end
$scope module _59_ $end
$var wire 1 w A $end
$var wire 1 x B $end
$var wire 1 \ Y $end
$upscope $end
$scope module _60_ $end
$var wire 1 j A $end
$var wire 1 i B $end
$var wire 1 [ Y $end
$upscope $end
$scope module _61_ $end
$var wire 1 y A $end
$var wire 1 [ B $end
$var wire 1 Z Y $end
$upscope $end
$scope module _62_ $end
$var wire 1 \ A $end
$var wire 1 Z B $end
$var wire 1 Y Y $end
$upscope $end
$scope module _63_ $end
$var wire 1 z A $end
$var wire 1 { B $end
$var wire 1 X Y $end
$upscope $end
$scope module _64_ $end
$var wire 1 h A $end
$var wire 1 g B $end
$var wire 1 W Y $end
$upscope $end
$scope module _65_ $end
$var wire 1 | A $end
$var wire 1 X B $end
$var wire 1 V Y $end
$upscope $end
$scope module _66_ $end
$var wire 1 } A $end
$var wire 1 Y B $end
$var wire 1 U Y $end
$upscope $end
$scope module _67_ $end
$var wire 1 W A $end
$var wire 1 U B $end
$var wire 1 5 Y $end
$upscope $end
$scope module _68_ $end
$var wire 1 ~ A $end
$var wire 1 ` B $end
$var wire 1 T Y $end
$upscope $end
$scope module _69_ $end
$var wire 1 Y A $end
$var wire 1 T B $end
$var wire 1 8 Y $end
$upscope $end
$scope module _70_ $end
$var wire 1 g A $end
$var wire 1 a B $end
$var wire 1 S Y $end
$upscope $end
$scope module _71_ $end
$var wire 1 !" A $end
$var wire 1 "" B $end
$var wire 1 R Y $end
$upscope $end
$scope module _72_ $end
$var wire 1 #" A $end
$var wire 1 $" B $end
$var wire 1 Q Y $end
$upscope $end
$scope module _73_ $end
$var wire 1 R A $end
$var wire 1 Q B $end
$var wire 1 P Y $end
$upscope $end
$scope module _74_ $end
$var wire 1 S A $end
$var wire 1 P B $end
$var wire 1 O Y $end
$upscope $end
$scope module _75_ $end
$var wire 1 %" A $end
$var wire 1 &" B $end
$var wire 1 N Y $end
$upscope $end
$scope module _76_ $end
$var wire 1 h A $end
$var wire 1 f B $end
$var wire 1 M Y $end
$upscope $end
$scope module _77_ $end
$var wire 1 O A $end
$var wire 1 M B $end
$var wire 1 3 Y $end
$upscope $end
$scope module _78_ $end
$var wire 1 L Y $end
$var wire 1 % B $end
$var wire 1 ( A $end
$upscope $end
$scope module _79_ $end
$var wire 1 c A $end
$var wire 1 L B $end
$var wire 1 K Y $end
$upscope $end
$scope module _80_ $end
$var wire 1 ^ A $end
$var wire 1 K B $end
$var wire 1 J Y $end
$upscope $end
$scope module _81_ $end
$var wire 1 J A $end
$var wire 1 1 Y $end
$upscope $end
$scope module _82_ $end
$var wire 1 f A $end
$var wire 1 O B $end
$var wire 1 I Y $end
$upscope $end
$scope module _83_ $end
$var wire 1 '" A $end
$var wire 1 I B $end
$var wire 1 H Y $end
$upscope $end
$scope module _84_ $end
$var wire 1 8 A $end
$var wire 1 H B $end
$var wire 1 G Y $end
$upscope $end
$scope module _85_ $end
$var wire 1 G A $end
$var wire 1 (" Y $end
$upscope $end
$scope module _86_ $end
$var wire 1 b A $end
$var wire 1 G B $end
$var wire 1 )" Y $end
$upscope $end
$scope module _87_ $end
$var wire 1 *" A $end
$var wire 1 N B $end
$var wire 1 F Y $end
$upscope $end
$scope module _88_ $end
$var wire 1 J A $end
$var wire 1 F B $end
$var wire 1 E Y $end
$upscope $end
$scope module _89_ $end
$var wire 1 8 A $end
$var wire 1 E B $end
$var wire 1 D Y $end
$upscope $end
$scope module _90_ $end
$var wire 1 D A $end
$var wire 1 +" Y $end
$upscope $end
$scope module _91_ $end
$var wire 1 b A $end
$var wire 1 D B $end
$var wire 1 ," Y $end
$upscope $end
$scope module _92_ $end
$var wire 1 V A $end
$var wire 1 T B $end
$var wire 1 C Y $end
$upscope $end
$scope module _93_ $end
$var wire 1 Y A $end
$var wire 1 C B $end
$var wire 1 B Y $end
$upscope $end
$scope module _94_ $end
$var wire 1 B A $end
$var wire 1 -" Y $end
$upscope $end
$scope module _95_ $end
$var wire 1 b A $end
$var wire 1 B B $end
$var wire 1 ." Y $end
$upscope $end
$scope module _96_ $end
$var wire 1 /" D $end
$var wire 1 7 C $end
$var reg 1 0" Q $end
$upscope $end
$scope module _97_ $end
$var wire 1 1" D $end
$var wire 1 7 C $end
$var reg 1 2" Q $end
$upscope $end
$scope module _98_ $end
$var wire 1 3" D $end
$var wire 1 7 C $end
$var reg 1 4" Q $end
$upscope $end
$upscope $end
$scope module probador $end
$var wire 1 9 active_out $end
$var wire 1 8 active_out_estr $end
$var wire 1 6 error_out $end
$var wire 1 5 error_out_estr $end
$var wire 1 4 idle_out $end
$var wire 1 3 idle_out_estr $end
$var wire 1 2 init_out $end
$var wire 1 1 init_out_estr $end
$var wire 1 * umbralD_out $end
$var wire 1 ) umbralD_out_estr $end
$var wire 1 ' umbralMF_out $end
$var wire 1 & umbralMF_out_estr $end
$var wire 1 $ umbralVC_out $end
$var wire 1 # umbralVC_out_estr $end
$var reg 5 5" Fifo_empties [4:0] $end
$var reg 5 6" Fifo_errors [4:0] $end
$var reg 1 7 clk $end
$var reg 1 . reset $end
$var reg 1 + umbralD $end
$var reg 1 ( umbralMF $end
$var reg 1 % umbralVC $end
$upscope $end
$upscope $end
$scope module DFFSR $end
$var wire 1 7" C $end
$var wire 1 8" D $end
$var wire 1 9" R $end
$var wire 1 :" S $end
$var reg 1 ;" Q $end
$upscope $end
$enddefinitions $end
#0
$dumpvars
x;"
z:"
z9"
z8"
z7"
b0 6"
b11111 5"
x4"
03"
x2"
01"
x0"
0/"
0."
0-"
0,"
x+"
x*"
0)"
x("
x'"
x&"
x%"
1$"
1#"
1""
1!"
x~
x}
x|
x{
xz
0y
0x
0w
xv
xu
xt
1s
xr
xq
xp
0o
0n
b11111 m
b0 l
b0 k
1j
1i
xh
xg
xf
1e
1d
1c
1b
0a
x`
x_
x^
x]
1\
0[
1Z
0Y
xX
xW
xV
1U
xT
xS
0R
0Q
1P
xO
xN
xM
1L
0K
1J
xI
xH
xG
xF
xE
xD
xC
1B
b0xx A
b0xxx @
bx ?
b0 >
b11111 =
b0 <
b11111 ;
b0 :
09
x8
07
06
05
04
x3
02
01
b0 0
b0xx /
0.
bx -
b0xxx ,
0+
0*
0)
0(
0'
0&
0%
0$
0#
z"
z!
$end
#4
1("
0G
1H
b1 /
b1 A
0+"
03
0I
1D
1]
1O
0^
0E
08
0C
0`
0W
0S
0M
1/"
01"
1_
1F
1T
1X
1N
1V
1)"
b1 k
0,"
1h
1g
1f
b1 0
b1 >
0'"
0%"
0z
0u
0p
0*"
0~
0{
0v
0q
0&"
0}
0|
0t
0r
0b
b0 -
b0 ?
00"
02"
b0 ,
b0 @
04"
1.
17
#8
07
#12
11"
1,"
1+"
0D
1E
0/"
11
1)
1#
1&
b10 k
0)"
0J
b10 /
b10 A
0("
0]
1G
1^
1`
1W
1M
1K
0H
0N
0X
0_
0L
0h
0c
0d
0e
1'"
1%"
1z
1u
1p
b10 0
b10 >
1*
1$
1'
12
1+
1%
1(
b1 ,
b1 @
10"
b1 -
b1 ?
17
#16
07
#20
0/"
13
1I
b10 k
0)"
b10 /
b10 A
0("
01
0)
0#
0&
0O
1G
0F
08
0C
1J
0`
0M
1]
1S
0H
1N
1_
1T
0^
1h
0g
14
0*
0$
0'
02
0'"
0%"
0z
0u
0p
1*"
1~
1{
1v
1q
b10 -
b10 ?
00"
b10 ,
b10 @
12"
17
#24
07
#28
1/"
b11 k
1)"
b11 /
b11 A
1("
0G
1H
03
0I
1O
0P
1R
0""
0!"
b11 0
b11 >
04
b11001 ;
b11001 =
b11001 m
b11001 5"
17
#32
07
#36
1/"
18
1C
b11 k
1)"
0E
b11 /
b11 A
1("
0T
0G
1F
1`
1M
0H
0N
0_
1Q
0h
1'"
1%"
1z
1u
1p
0#"
19
b11 -
b11 ?
b11 ,
b11 @
10"
b10001 ;
b10001 =
b10001 m
b10001 5"
17
#40
07
#44
0/"
01"
0)"
0,"
0("
0+"
13"
1G
1D
b100 k
1."
b100 /
b100 A
1-"
08
0B
1Y
0\
1w
b100 0
b100 >
09
b1 :
b1 <
b1 l
b1 6"
17
#48
07
#52
01"
0,"
13"
0+"
1."
1D
0/"
1-"
b100 k
0)"
0B
0E
b100 /
b100 A
0("
01
15
1G
1C
0V
1J
0W
0S
1I
0H
1_
1T
1X
0^
0U
0`
1h
1g
0f
16
0'"
0%"
0z
0u
0p
0*"
0~
0{
0v
0q
1&"
1}
1|
1t
1r
b100 -
b100 ?
00"
02"
b100 ,
b100 @
14"
17
#56
07
#60
03"
05
b0 k
0."
b0 /
b0 A
0-"
1U
1B
0Y
1\
0w
b0 0
b0 >
06
b0 :
b0 <
b0 l
b0 6"
17
#64
07
#68
1/"
b1 k
1)"
b1 /
b1 A
1("
0G
1H
0C
0M
0I
1N
1V
1f
b1 0
b1 >
0&"
0}
0|
0t
0r
b0 -
b0 ?
b0 ,
b0 @
04"
17
#72
07
#76
11"
1,"
1+"
0D
1E
0/"
11
1)
1#
1&
b10 k
0)"
0J
b10 /
b10 A
0("
0]
1G
1^
1`
1W
1M
0H
0N
0X
0_
0h
1'"
1%"
1z
1u
1p
b10 0
b10 >
1*
1$
1'
12
b1 ,
b1 @
10"
b1 -
b1 ?
17
