Memoria/probador.v
module probador #(parameter BITNUMBER =10,
		parameter LENGTH = 8)
(input [BITNUMBER-1:0] data_out,
	output reg reset,
	output reg clk,
	output reg read,
	output reg write,
	output reg [2:0] ptr_write,
	output reg [2:0] ptr_read,
	output reg [BITNUMBER-1:0] data_in);

initial begin
	$dumpfile("resultados.vcd");
	$dumpvars;
	reset <=0;
	read <=0;
	write <=0;
	data_in <=0;
	ptr_write <=0;
	ptr_read <=0;
	@(posedge clk);
	@(posedge clk);
	reset <=1;
	@(posedge clk);
	data_in<=1;
	ptr_write<=1;
	write <=1;
	@(posedge clk);
	data_in<=2;
	ptr_read<=0;
	read<=1;
	ptr_write<=2;
	write<=1;
	@(posedge clk);
	data_in<=3;
	ptr_read<=1;
	read<=1;
	ptr_write<=3;
	write<=1;
	@(posedge clk);
	data_in<=4;
	ptr_read<=2;
	read<=1;
	ptr_write<=1;//orignalmente era 0
	write<=1;
	@(posedge clk);
	data_in<=5;
	ptr_read<=3;
	read<=1;
	ptr_write<=1;
	write<=1;	//Empezamos una mini prueba
	@(posedge clk);
	data_in<=6;
	ptr_read<=4;
	read<=1;
	ptr_write<=2;
	write<=1; //Extendemos la senal
	@(posedge clk);
	data_in<=7;
	ptr_read<=5;
	read<=1;
	ptr_write<=0;
	write<=0;
	@(posedge clk);
	data_in<=8;
	ptr_read<=6;
	read<=1;
	ptr_write<=2;
	write<=0;
	@(posedge clk);
	@(posedge clk);
	$finish;	
end

initial clk <=0;
always #4 clk <= ~clk;
endmodule

Memoria/memoria.v
module memoria #(parameter BITNUMBER = 10,
			parameter LENGTH = 8)
(input [BITNUMBER-1:0] data_in,
	input [2:0] ptr_write,
	input [2:0] ptr_read,
	input reset, 
	input clk, 
	input read,
	input write,
	output reg [BITNUMBER-1:0] data_out);	

	reg [BITNUMBER-1:0] mem [LENGTH-1:0];
	integer k;

	always@(posedge clk) begin
		if(~reset) begin
			for(k = 0; k<LENGTH ; k = k+1 )begin 
				mem[k] <= 'b0; //Se pone en bajo las posiciones en la memoria
			end
		end else begin  
			  	if (write) mem[ptr_write] <= data_in;//Escribimos el dato de entrada en la posicion
				
		end
	end

	always@(*) begin
		data_out =0;
		if (read) data_out= mem[ptr_read];
	end


endmodule

Memoria/BancoPruebas.v
`timescale 1ns / 100ps
`include "memoria.v"
`include "probador.v"

module BancoPruebas;

//Parametros
parameter BITNUMBER =10;
parameter LENGTH =8;

//Wires
wire clk, reset, read, write;
wire [2:0] ptr_write, ptr_read;
wire [BITNUMBER-1:0] data_in;
wire [BITNUMBER-1:0] data_out;

memoria memoria(.data_in	(data_in),
		.data_out	(data_out),
		.ptr_write	(ptr_write),
		.ptr_read	(ptr_read),
		.clk		(clk),
		.reset		(reset),
		.read		(read),
		.write		(write));

probador probador(.data_in	(data_in),
		.data_out	(data_out),
		.ptr_write	(ptr_write),
		.ptr_read	(ptr_read),
		.clk		(clk),
		.reset		(reset),
		.read		(read),
		.write		(write));

endmodule

Memoria/resultados.vcd
$date
	Mon Oct 26 15:23:55 2020
$end
$version
	Icarus Verilog
$end
$timescale
	100ps
$end
$scope module BancoPruebas $end
$var wire 1 ! write $end
$var wire 1 " reset $end
$var wire 1 # read $end
$var wire 3 $ ptr_write [2:0] $end
$var wire 3 % ptr_read [2:0] $end
$var wire 10 & data_out [9:0] $end
$var wire 10 ' data_in [9:0] $end
$var wire 1 ( clk $end
$scope module memoria $end
$var wire 1 ! write $end
$var wire 1 " reset $end
$var wire 1 # read $end
$var wire 3 ) ptr_write [2:0] $end
$var wire 3 * ptr_read [2:0] $end
$var wire 10 + data_in [9:0] $end
$var wire 1 ( clk $end
$var reg 10 , data_out [9:0] $end
$var integer 32 - k [31:0] $end
$upscope $end
$scope module probador $end
$var wire 10 . data_out [9:0] $end
$var reg 1 ( clk $end
$var reg 10 / data_in [9:0] $end
$var reg 3 0 ptr_read [2:0] $end
$var reg 3 1 ptr_write [2:0] $end
$var reg 1 # read $end
$var reg 1 " reset $end
$var reg 1 ! write $end
$upscope $end
$upscope $end
$enddefinitions $end
#0
$dumpvars
b0 1
b0 0
b0 /
b0 .
bx -
b0 ,
b0 +
b0 *
b0 )
0(
b0 '
b0 &
b0 %
b0 $
0#
0"
0!
$end
#40
b1000 -
1(
#80
0(
#120
1"
b1000 -
1(
#160
0(
#200
1!
b1 $
b1 )
b1 1
b1 '
b1 +
b1 /
1(
#240
0(
#280
b10 $
b10 )
b10 1
1#
b10 '
b10 +
b10 /
1(
#320
0(
#360
b1 &
b1 ,
b1 .
b11 $
b11 )
b11 1
b1 %
b1 *
b1 0
b11 '
b11 +
b11 /
1(
#400
0(
#440
b10 &
b10 ,
b10 .
b1 $
b1 )
b1 1
b10 %
b10 *
b10 0
b100 '
b100 +
b100 /
1(
#480
0(
#520
b11 &
b11 ,
b11 .
b11 %
b11 *
b11 0
b101 '
b101 +
b101 /
1(
#560
0(
#600
b0 &
b0 ,
b0 .
b10 $
b10 )
b10 1
b100 %
b100 *
b100 0
b110 '
b110 +
b110 /
1(
#640
0(
#680
0!
b0 $
b0 )
b0 1
b101 %
b101 *
b101 0
b111 '
b111 +
b111 /
1(
#720
0(
#760
b10 $
b10 )
b10 1
b110 %
b110 *
b110 0
b1000 '
b1000 +
b1000 /
1(
