Maquina_test/probador.v
module probador(input idle_out, active_out, error_out, init_out,
		input idle_out_estr, active_out_estr, error_out_estr, init_out_estr,
		output reg clk,
		output reg reset,
		output reg umbralMF, umbralVC, umbralD,
		output reg FifoFull, FifoEmpty, FifoRead, FifoWrite);
		
	initial begin
		$dumpfile("resultados.vcd");
		$dumpvars;
		
		reset<=0;
		umbralMF<=0;
		umbralVC<=0;
		umbralD<=0;
		FifoFull<=0;
		FifoEmpty<=0;
		FifoRead<=0;
		FifoWrite<=0;
		
		@(posedge clk);
		//@(posedge clk);
		reset<=1;
		@(posedge clk);
		//@(posedge clk);
		umbralMF<=1;
		umbralVC<=1;
		umbralD<=0;
		FifoEmpty<=0; //Este cambio a 0 funciona, aqui se prende init_out
		@(posedge clk);
		//@(posedge clk);
		FifoEmpty<=1;
		FifoFull<=0;
		@(posedge clk); //Repetimos --- Se esta repitiendo estado 2 = IDLE
		FifoEmpty<=0;
		FifoFull<=0;
		@(posedge clk); //Aqui cambie las senales de  0 y 0 a 1 y 1
		FifoEmpty<=0;
		FifoFull<=0;
		//Voy a agregar un pulso extra para activar el error
		@(posedge clk);
		FifoEmpty<=1;
		FifoFull<=1;
		@(posedge clk); //Se deberia estar en el estado de ERROR
		FifoEmpty<=0;
		FifoFull<=1;
		FifoRead<=1;
		FifoWrite<=1;
		@(posedge clk);
		FifoFull<=0;
		FifoRead<=0;
		FifoWrite<=0;
		@(posedge clk);
		$finish;
		
		
	end		
	
	
	
initial clk <=0;
always #4 clk <= ~clk;
endmodule

Maquina_test/maquina_synth.v
/* Generated by Yosys 0.7 (git sha1 61f6811, gcc 6.2.0-11ubuntu1 -O2 -fdebug-prefix-map=/build/yosys-OIL3SR/yosys-0.7=. -fstack-protector-strong -fPIC -Os) */

(* top =  1  *)
(* src = "maquina.v:1" *)
module maquina_synth(clk, reset, umbralMF, umbralVC, umbralD, FifoFull, FifoEmpty, FifoWrite, FifoRead, init_out, idle_out, active_out, error_out, state_estr, next_state_estr);
  (* src = "maquina.v:23" *)
  wire [3:0] _000_;
  wire _001_;
  wire _002_;
  wire _003_;
  wire _004_;
  wire _005_;
  wire _006_;
  wire _007_;
  wire _008_;
  wire _009_;
  wire _010_;
  wire _011_;
  wire _012_;
  wire _013_;
  wire _014_;
  wire _015_;
  wire _016_;
  wire _017_;
  wire _018_;
  wire _019_;
  wire _020_;
  wire _021_;
  wire _022_;
  wire _023_;
  wire _024_;
  wire _025_;
  wire _026_;
  wire _027_;
  wire _028_;
  wire _029_;
  wire _030_;
  wire _031_;
  wire _032_;
  wire _033_;
  wire _034_;
  wire _035_;
  wire _036_;
  wire _037_;
  wire _038_;
  wire _039_;
  wire _040_;
  wire _041_;
  wire _042_;
  wire _043_;
  wire _044_;
  wire _045_;
  wire _046_;
  wire _047_;
  wire _048_;
  wire _049_;
  wire _050_;
  (* src = "maquina.v:7" *)
  input FifoEmpty;
  (* src = "maquina.v:6" *)
  input FifoFull;
  (* src = "maquina.v:9" *)
  input FifoRead;
  (* src = "maquina.v:8" *)
  input FifoWrite;
  (* src = "maquina.v:12" *)
  output active_out;
  (* src = "maquina.v:1" *)
  input clk;
  (* src = "maquina.v:13" *)
  output error_out;
  (* src = "maquina.v:11" *)
  output idle_out;
  (* src = "maquina.v:10" *)
  output init_out;
  (* src = "maquina.v:15" *)
  output [3:0] next_state_estr;
  (* src = "maquina.v:2" *)
  input reset;
  (* src = "maquina.v:14" *)
  output [3:0] state_estr;
  (* src = "maquina.v:5" *)
  input umbralD;
  (* src = "maquina.v:3" *)
  input umbralMF;
  (* src = "maquina.v:4" *)
  input umbralVC;
  NOR _051_ (
    .A(FifoFull),
    .B(FifoEmpty),
    .Y(_001_)
  );
  NOT _052_ (
    .A(state_estr[0]),
    .Y(_002_)
  );
  NOR _053_ (
    .A(state_estr[2]),
    .B(state_estr[3]),
    .Y(_003_)
  );
  NAND _054_ (
    .A(_003_),
    .B(state_estr[1]),
    .Y(_004_)
  );
  NOR _055_ (
    .A(_004_),
    .B(_002_),
    .Y(_005_)
  );
  NAND _056_ (
    .A(_005_),
    .B(_001_),
    .Y(_006_)
  );
  NOT _057_ (
    .A(_006_),
    .Y(active_out)
  );
  NOT _058_ (
    .A(state_estr[1]),
    .Y(_007_)
  );
  NOT _059_ (
    .A(state_estr[3]),
    .Y(_008_)
  );
  NOT _060_ (
    .A(state_estr[2]),
    .Y(_009_)
  );
  NAND _061_ (
    .A(_009_),
    .B(_008_),
    .Y(_010_)
  );
  NOR _062_ (
    .A(_010_),
    .B(_007_),
    .Y(_011_)
  );
  NAND _063_ (
    .A(_011_),
    .B(_002_),
    .Y(_012_)
  );
  NOT _064_ (
    .A(FifoFull),
    .Y(_013_)
  );
  NAND _065_ (
    .A(_013_),
    .B(FifoEmpty),
    .Y(_014_)
  );
  NOR _066_ (
    .A(_014_),
    .B(_012_),
    .Y(idle_out)
  );
  NAND _067_ (
    .A(_007_),
    .B(state_estr[0]),
    .Y(_015_)
  );
  NOT _068_ (
    .A(umbralVC),
    .Y(_016_)
  );
  NOR _069_ (
    .A(umbralD),
    .B(umbralMF),
    .Y(_017_)
  );
  NAND _070_ (
    .A(_017_),
    .B(_016_),
    .Y(_018_)
  );
  NAND _071_ (
    .A(_018_),
    .B(_003_),
    .Y(_019_)
  );
  NOR _072_ (
    .A(_019_),
    .B(_015_),
    .Y(init_out)
  );
  NAND _073_ (
    .A(FifoFull),
    .B(FifoEmpty),
    .Y(_020_)
  );
  NAND _074_ (
    .A(_020_),
    .B(_005_),
    .Y(_021_)
  );
  NOR _075_ (
    .A(state_estr[0]),
    .B(state_estr[3]),
    .Y(_022_)
  );
  NAND _076_ (
    .A(_022_),
    .B(_009_),
    .Y(_023_)
  );
  NOR _077_ (
    .A(_001_),
    .B(_007_),
    .Y(_024_)
  );
  NOR _078_ (
    .A(_024_),
    .B(_023_),
    .Y(_025_)
  );
  NOT _079_ (
    .A(_025_),
    .Y(_026_)
  );
  NAND _080_ (
    .A(_026_),
    .B(_021_),
    .Y(next_state_estr[0])
  );
  NOT _081_ (
    .A(reset),
    .Y(_027_)
  );
  NAND _082_ (
    .A(_011_),
    .B(state_estr[0]),
    .Y(_028_)
  );
  NOT _083_ (
    .A(_020_),
    .Y(_029_)
  );
  NOR _084_ (
    .A(_029_),
    .B(_028_),
    .Y(_030_)
  );
  NOR _085_ (
    .A(_025_),
    .B(_030_),
    .Y(_031_)
  );
  NOR _086_ (
    .A(_031_),
    .B(_027_),
    .Y(_000_[0])
  );
  NOR _087_ (
    .A(_029_),
    .B(_012_),
    .Y(_032_)
  );
  NOR _088_ (
    .A(_032_),
    .B(init_out),
    .Y(_033_)
  );
  NAND _089_ (
    .A(_033_),
    .B(_006_),
    .Y(next_state_estr[1])
  );
  NOR _090_ (
    .A(_015_),
    .B(_010_),
    .Y(_034_)
  );
  NAND _091_ (
    .A(_034_),
    .B(_018_),
    .Y(_035_)
  );
  NAND _092_ (
    .A(_035_),
    .B(_006_),
    .Y(_036_)
  );
  NOR _093_ (
    .A(_036_),
    .B(_032_),
    .Y(_037_)
  );
  NOR _094_ (
    .A(_037_),
    .B(_027_),
    .Y(_000_[1])
  );
  NOR _095_ (
    .A(_020_),
    .B(_004_),
    .Y(_038_)
  );
  NOT _096_ (
    .A(_038_),
    .Y(_039_)
  );
  NAND _097_ (
    .A(state_estr[2]),
    .B(_007_),
    .Y(_040_)
  );
  NOR _098_ (
    .A(_040_),
    .B(_013_),
    .Y(_041_)
  );
  NOT _099_ (
    .A(_022_),
    .Y(_042_)
  );
  NOR _100_ (
    .A(FifoWrite),
    .B(FifoRead),
    .Y(_043_)
  );
  NOR _101_ (
    .A(_043_),
    .B(_042_),
    .Y(_044_)
  );
  NAND _102_ (
    .A(_044_),
    .B(_041_),
    .Y(_045_)
  );
  NAND _103_ (
    .A(_045_),
    .B(_039_),
    .Y(next_state_estr[2])
  );
  NAND _104_ (
    .A(_022_),
    .B(state_estr[2]),
    .Y(_046_)
  );
  NOR _105_ (
    .A(_046_),
    .B(_043_),
    .Y(_047_)
  );
  NAND _106_ (
    .A(_047_),
    .B(_007_),
    .Y(_048_)
  );
  NOR _107_ (
    .A(_048_),
    .B(_013_),
    .Y(_049_)
  );
  NOR _108_ (
    .A(_049_),
    .B(_038_),
    .Y(_050_)
  );
  NOR _109_ (
    .A(_050_),
    .B(_027_),
    .Y(_000_[2])
  );
  DFF _110_ (
    .C(clk),
    .D(_000_[0]),
    .Q(state_estr[0])
  );
  DFF _111_ (
    .C(clk),
    .D(_000_[1]),
    .Q(state_estr[1])
  );
  DFF _112_ (
    .C(clk),
    .D(_000_[2]),
    .Q(state_estr[2])
  );
  DFF _113_ (
    .C(clk),
    .D(1'b0),
    .Q(state_estr[3])
  );
  assign error_out = 1'b0;
  assign next_state_estr[3] = 1'b0;
endmodule

Maquina_test/maquina.v
module maquina(input clk,
		input reset,
		input umbralMF,
		input umbralVC,
		input umbralD,
		input FifoFull,
		input FifoEmpty,
		input FifoWrite,
		input FifoRead,
		output reg init_out,
		output reg idle_out,
		output reg active_out,
		output reg error_out,
		output reg [3:0] state, 
		output reg [3:0]next_state);

parameter RESET=0;
parameter INIT =1;
parameter IDLE =2;
parameter ACTIVE=3;
parameter ERROR=4;

 always @ (posedge clk) begin
        if(~reset) begin
            state <= RESET; 
            error_out <=0;
        end
        else begin
            state <= next_state;
            
        end
    end		

always @(*) begin
	idle_out=0;
	active_out=0;
	error_out=0;
	next_state=state;
	init_out = 0;
	case(state)
		RESET: begin
		//For RESET state
			next_state= INIT;
		end
		
		INIT: begin
		//For INIT state
			if(umbralMF==1 || umbralVC==1 || umbralD==1)begin
			//Si hay algun umbral ON, init_out se enciende
				init_out=1;
				next_state= IDLE;
			end else begin
			//Si ningun umbral esta on, se vuelve a RESET e init_out se queda apagado
				init_out=0;
				next_state= RESET;
			end
		end
		
		IDLE: begin
		//For IDLE state
			if(FifoEmpty==1 && FifoFull==0)begin 
				idle_out=1;
				next_state= IDLE;
			end if (FifoEmpty==1 && FifoFull==1)begin
				idle_out=0;
				next_state= ERROR;
			end if (FifoEmpty==0 && FifoFull==0) begin
			//Si hay un FIFO no vacio entonces pasamos a ACTIVE, osea FifoEmpty==0
				idle_out=0;
				next_state= ACTIVE;
			
			end
		end
		
		ACTIVE: begin
		//For ACTIVE state
			if(FifoEmpty==0 && FifoFull==0) begin //Si el fifo no esta ni lleno, ni vacio, osea que tiene informacion adentro que se puede transmitir
				active_out=1;
				next_state=ACTIVE;
			end else if(FifoEmpty==1 && FifoFull==1) begin
			//Este caso generaria un error puesto que el fifo no puede estar vacio y lleno al mismo tiempo
				active_out=0;
				next_state=ERROR; 	
			end else begin
				active_out=0;
				next_state=INIT;
			end
			
		end
		
		ERROR: begin
		//For ERROR state
			if(FifoRead==1 && FifoFull==1)begin
				error_out=1;
				next_state=ERROR;
			end else if (FifoFull==1 && FifoWrite==1 && FifoRead==0) begin
				error_out=1;
				next_state=ERROR;
			end else begin
				error_out=0;
				next_state=RESET;
			end		
		end
		default: begin
			next_state= RESET;
			idle_out=0;
			active_out=0;
			error_out=0;
		end
	endcase	
end


endmodule

Maquina_test/BancoPruebas.v
`include "maquina.v"
`include "probador.v"
`include "cmos_cells.v"
`include "maquina_synth.v"

module BancoPruebas;

wire clk, reset;

wire umbralMF, umbralVC, umbralD;
wire FifoFull, FifoEmpty, FifoRead, FifoWrite;

wire init_out, idle_out, active_out, error_out;
wire idle_out_estr, active_out_estr, error_out_estr, init_out_estr;
wire [3:0] next_state, next_state_estr, state, state_estr;

maquina maquina(.clk	(clk),
		.reset	(reset),
		.umbralMF	(umbralMF),
		.umbralVC	(umbralVC),
		.umbralD	(umbralD),
		.FifoFull	(FifoFull),
		.FifoEmpty	(FifoEmpty),
		.FifoRead	(FifoRead),
		.FifoWrite	(FifoWrite),
		.init_out	(init_out),
		.idle_out	(idle_out),
		.active_out	(active_out),
		.error_out	(error_out),
		.state		(state[3:0]),
		.next_state (next_state[3:0]));

maquina_synth maquina_synth(.clk	(clk),
		.reset	(reset),
		.umbralMF	(umbralMF),
		.umbralVC	(umbralVC),
		.umbralD	(umbralD),
		.FifoFull	(FifoFull),
		.FifoEmpty	(FifoEmpty),
		.FifoRead	(FifoRead),
		.FifoWrite	(FifoWrite),
		.init_out	(init_out_estr),
		.idle_out	(idle_out_estr),
		.active_out	(active_out_estr),
		.error_out	(error_out_estr),
		.state_estr		(state_estr[3:0]),
		.next_state_estr (next_state_estr[3:0]));		

probador probador(.clk	(clk),
		.reset	(reset),
		.umbralMF	(umbralMF),
		.umbralVC	(umbralVC),
		.umbralD	(umbralD),
		.FifoFull	(FifoFull),
		.FifoEmpty	(FifoEmpty),
		.FifoRead	(FifoRead),
		.FifoWrite	(FifoWrite),
		.init_out_estr	(init_out_estr),
		.idle_out_estr	(idle_out_estr),
		.active_out_estr	(active_out_estr),
		.error_out_estr	(error_out_estr),
		.init_out	(init_out),
		.idle_out	(idle_out),
		.active_out	(active_out),
		.error_out	(error_out));

endmodule

Memoria/cmos_cells.v

module BUF(A, Y);
input A;
output Y;
assign Y = A;
endmodule

module NOT(A, Y);
input A;
output Y;
assign Y = ~A;
endmodule

module NAND(A, B, Y);
input A, B;
output Y;
assign Y = ~(A & B);
endmodule

module NOR(A, B, Y);
input A, B;
output Y;
assign Y = ~(A | B);
endmodule

module DFF(C, D, Q);
input C, D;
output reg Q;
always @(posedge C)
	Q <= D;
endmodule

module DFFSR(C, D, Q, S, R);
input C, D, S, R;
output reg Q;
always @(posedge C, posedge S, posedge R)
	if (S)
		Q <= 1'b1;
	else if (R)
		Q <= 1'b0;
	else
		Q <= D;
endmodule

Maquina_test/resultados.vcd
$date
	Tue Nov  3 22:03:28 2020
$end
$version
	Icarus Verilog
$end
$timescale
	1s
$end
$scope module BUF $end
$var wire 1 ! A $end
$var wire 1 " Y $end
$upscope $end
$scope module BancoPruebas $end
$var wire 1 # error_out_estr $end
$var wire 1 $ umbralVC $end
$var wire 1 % umbralMF $end
$var wire 1 & umbralD $end
$var wire 4 ' state_estr [3:0] $end
$var wire 4 ( state [3:0] $end
$var wire 1 ) reset $end
$var wire 4 * next_state_estr [3:0] $end
$var wire 4 + next_state [3:0] $end
$var wire 1 , init_out_estr $end
$var wire 1 - init_out $end
$var wire 1 . idle_out_estr $end
$var wire 1 / idle_out $end
$var wire 1 0 error_out $end
$var wire 1 1 clk $end
$var wire 1 2 active_out_estr $end
$var wire 1 3 active_out $end
$var wire 1 4 FifoWrite $end
$var wire 1 5 FifoRead $end
$var wire 1 6 FifoFull $end
$var wire 1 7 FifoEmpty $end
$scope module maquina $end
$var wire 1 $ umbralVC $end
$var wire 1 % umbralMF $end
$var wire 1 & umbralD $end
$var wire 1 ) reset $end
$var wire 1 1 clk $end
$var wire 1 4 FifoWrite $end
$var wire 1 5 FifoRead $end
$var wire 1 6 FifoFull $end
$var wire 1 7 FifoEmpty $end
$var reg 1 3 active_out $end
$var reg 1 0 error_out $end
$var reg 1 / idle_out $end
$var reg 1 - init_out $end
$var reg 4 8 next_state [3:0] $end
$var reg 4 9 state [3:0] $end
$upscope $end
$scope module maquina_synth $end
$var wire 1 # error_out $end
$var wire 1 $ umbralVC $end
$var wire 1 % umbralMF $end
$var wire 1 & umbralD $end
$var wire 4 : state_estr [3:0] $end
$var wire 1 ) reset $end
$var wire 4 ; next_state_estr [3:0] $end
$var wire 1 , init_out $end
$var wire 1 . idle_out $end
$var wire 1 1 clk $end
$var wire 1 2 active_out $end
$var wire 1 < _050_ $end
$var wire 1 = _049_ $end
$var wire 1 > _048_ $end
$var wire 1 ? _047_ $end
$var wire 1 @ _046_ $end
$var wire 1 A _045_ $end
$var wire 1 B _044_ $end
$var wire 1 C _043_ $end
$var wire 1 D _042_ $end
$var wire 1 E _041_ $end
$var wire 1 F _040_ $end
$var wire 1 G _039_ $end
$var wire 1 H _038_ $end
$var wire 1 I _037_ $end
$var wire 1 J _036_ $end
$var wire 1 K _035_ $end
$var wire 1 L _034_ $end
$var wire 1 M _033_ $end
$var wire 1 N _032_ $end
$var wire 1 O _031_ $end
$var wire 1 P _030_ $end
$var wire 1 Q _029_ $end
$var wire 1 R _028_ $end
$var wire 1 S _027_ $end
$var wire 1 T _026_ $end
$var wire 1 U _025_ $end
$var wire 1 V _024_ $end
$var wire 1 W _023_ $end
$var wire 1 X _022_ $end
$var wire 1 Y _021_ $end
$var wire 1 Z _020_ $end
$var wire 1 [ _019_ $end
$var wire 1 \ _018_ $end
$var wire 1 ] _017_ $end
$var wire 1 ^ _016_ $end
$var wire 1 _ _015_ $end
$var wire 1 ` _014_ $end
$var wire 1 a _013_ $end
$var wire 1 b _012_ $end
$var wire 1 c _011_ $end
$var wire 1 d _010_ $end
$var wire 1 e _009_ $end
$var wire 1 f _008_ $end
$var wire 1 g _007_ $end
$var wire 1 h _006_ $end
$var wire 1 i _005_ $end
$var wire 1 j _004_ $end
$var wire 1 k _003_ $end
$var wire 1 l _002_ $end
$var wire 1 m _001_ $end
$var wire 4 n _000_ [3:0] $end
$var wire 1 4 FifoWrite $end
$var wire 1 5 FifoRead $end
$var wire 1 6 FifoFull $end
$var wire 1 7 FifoEmpty $end
$scope module _051_ $end
$var wire 1 m Y $end
$var wire 1 7 B $end
$var wire 1 6 A $end
$upscope $end
$scope module _052_ $end
$var wire 1 o A $end
$var wire 1 l Y $end
$upscope $end
$scope module _053_ $end
$var wire 1 p A $end
$var wire 1 q B $end
$var wire 1 k Y $end
$upscope $end
$scope module _054_ $end
$var wire 1 k A $end
$var wire 1 r B $end
$var wire 1 j Y $end
$upscope $end
$scope module _055_ $end
$var wire 1 j A $end
$var wire 1 l B $end
$var wire 1 i Y $end
$upscope $end
$scope module _056_ $end
$var wire 1 i A $end
$var wire 1 m B $end
$var wire 1 h Y $end
$upscope $end
$scope module _057_ $end
$var wire 1 h A $end
$var wire 1 2 Y $end
$upscope $end
$scope module _058_ $end
$var wire 1 s A $end
$var wire 1 g Y $end
$upscope $end
$scope module _059_ $end
$var wire 1 t A $end
$var wire 1 f Y $end
$upscope $end
$scope module _060_ $end
$var wire 1 u A $end
$var wire 1 e Y $end
$upscope $end
$scope module _061_ $end
$var wire 1 e A $end
$var wire 1 f B $end
$var wire 1 d Y $end
$upscope $end
$scope module _062_ $end
$var wire 1 d A $end
$var wire 1 g B $end
$var wire 1 c Y $end
$upscope $end
$scope module _063_ $end
$var wire 1 c A $end
$var wire 1 l B $end
$var wire 1 b Y $end
$upscope $end
$scope module _064_ $end
$var wire 1 a Y $end
$var wire 1 6 A $end
$upscope $end
$scope module _065_ $end
$var wire 1 a A $end
$var wire 1 ` Y $end
$var wire 1 7 B $end
$upscope $end
$scope module _066_ $end
$var wire 1 ` A $end
$var wire 1 b B $end
$var wire 1 . Y $end
$upscope $end
$scope module _067_ $end
$var wire 1 g A $end
$var wire 1 v B $end
$var wire 1 _ Y $end
$upscope $end
$scope module _068_ $end
$var wire 1 ^ Y $end
$var wire 1 $ A $end
$upscope $end
$scope module _069_ $end
$var wire 1 ] Y $end
$var wire 1 % B $end
$var wire 1 & A $end
$upscope $end
$scope module _070_ $end
$var wire 1 ] A $end
$var wire 1 ^ B $end
$var wire 1 \ Y $end
$upscope $end
$scope module _071_ $end
$var wire 1 \ A $end
$var wire 1 k B $end
$var wire 1 [ Y $end
$upscope $end
$scope module _072_ $end
$var wire 1 [ A $end
$var wire 1 _ B $end
$var wire 1 , Y $end
$upscope $end
$scope module _073_ $end
$var wire 1 Z Y $end
$var wire 1 7 B $end
$var wire 1 6 A $end
$upscope $end
$scope module _074_ $end
$var wire 1 Z A $end
$var wire 1 i B $end
$var wire 1 Y Y $end
$upscope $end
$scope module _075_ $end
$var wire 1 w A $end
$var wire 1 x B $end
$var wire 1 X Y $end
$upscope $end
$scope module _076_ $end
$var wire 1 X A $end
$var wire 1 e B $end
$var wire 1 W Y $end
$upscope $end
$scope module _077_ $end
$var wire 1 m A $end
$var wire 1 g B $end
$var wire 1 V Y $end
$upscope $end
$scope module _078_ $end
$var wire 1 V A $end
$var wire 1 W B $end
$var wire 1 U Y $end
$upscope $end
$scope module _079_ $end
$var wire 1 U A $end
$var wire 1 T Y $end
$upscope $end
$scope module _080_ $end
$var wire 1 T A $end
$var wire 1 Y B $end
$var wire 1 y Y $end
$upscope $end
$scope module _081_ $end
$var wire 1 S Y $end
$var wire 1 ) A $end
$upscope $end
$scope module _082_ $end
$var wire 1 c A $end
$var wire 1 z B $end
$var wire 1 R Y $end
$upscope $end
$scope module _083_ $end
$var wire 1 Z A $end
$var wire 1 Q Y $end
$upscope $end
$scope module _084_ $end
$var wire 1 Q A $end
$var wire 1 R B $end
$var wire 1 P Y $end
$upscope $end
$scope module _085_ $end
$var wire 1 U A $end
$var wire 1 P B $end
$var wire 1 O Y $end
$upscope $end
$scope module _086_ $end
$var wire 1 O A $end
$var wire 1 S B $end
$var wire 1 { Y $end
$upscope $end
$scope module _087_ $end
$var wire 1 Q A $end
$var wire 1 b B $end
$var wire 1 N Y $end
$upscope $end
$scope module _088_ $end
$var wire 1 N A $end
$var wire 1 , B $end
$var wire 1 M Y $end
$upscope $end
$scope module _089_ $end
$var wire 1 M A $end
$var wire 1 h B $end
$var wire 1 | Y $end
$upscope $end
$scope module _090_ $end
$var wire 1 _ A $end
$var wire 1 d B $end
$var wire 1 L Y $end
$upscope $end
$scope module _091_ $end
$var wire 1 L A $end
$var wire 1 \ B $end
$var wire 1 K Y $end
$upscope $end
$scope module _092_ $end
$var wire 1 K A $end
$var wire 1 h B $end
$var wire 1 J Y $end
$upscope $end
$scope module _093_ $end
$var wire 1 J A $end
$var wire 1 N B $end
$var wire 1 I Y $end
$upscope $end
$scope module _094_ $end
$var wire 1 I A $end
$var wire 1 S B $end
$var wire 1 } Y $end
$upscope $end
$scope module _095_ $end
$var wire 1 Z A $end
$var wire 1 j B $end
$var wire 1 H Y $end
$upscope $end
$scope module _096_ $end
$var wire 1 H A $end
$var wire 1 G Y $end
$upscope $end
$scope module _097_ $end
$var wire 1 ~ A $end
$var wire 1 g B $end
$var wire 1 F Y $end
$upscope $end
$scope module _098_ $end
$var wire 1 F A $end
$var wire 1 a B $end
$var wire 1 E Y $end
$upscope $end
$scope module _099_ $end
$var wire 1 X A $end
$var wire 1 D Y $end
$upscope $end
$scope module _100_ $end
$var wire 1 C Y $end
$var wire 1 5 B $end
$var wire 1 4 A $end
$upscope $end
$scope module _101_ $end
$var wire 1 C A $end
$var wire 1 D B $end
$var wire 1 B Y $end
$upscope $end
$scope module _102_ $end
$var wire 1 B A $end
$var wire 1 E B $end
$var wire 1 A Y $end
$upscope $end
$scope module _103_ $end
$var wire 1 A A $end
$var wire 1 G B $end
$var wire 1 !" Y $end
$upscope $end
$scope module _104_ $end
$var wire 1 X A $end
$var wire 1 "" B $end
$var wire 1 @ Y $end
$upscope $end
$scope module _105_ $end
$var wire 1 @ A $end
$var wire 1 C B $end
$var wire 1 ? Y $end
$upscope $end
$scope module _106_ $end
$var wire 1 ? A $end
$var wire 1 g B $end
$var wire 1 > Y $end
$upscope $end
$scope module _107_ $end
$var wire 1 > A $end
$var wire 1 a B $end
$var wire 1 = Y $end
$upscope $end
$scope module _108_ $end
$var wire 1 = A $end
$var wire 1 H B $end
$var wire 1 < Y $end
$upscope $end
$scope module _109_ $end
$var wire 1 < A $end
$var wire 1 S B $end
$var wire 1 #" Y $end
$upscope $end
$scope module _110_ $end
$var wire 1 $" D $end
$var wire 1 1 C $end
$var reg 1 %" Q $end
$upscope $end
$scope module _111_ $end
$var wire 1 &" D $end
$var wire 1 1 C $end
$var reg 1 '" Q $end
$upscope $end
$scope module _112_ $end
$var wire 1 (" D $end
$var wire 1 1 C $end
$var reg 1 )" Q $end
$upscope $end
$scope module _113_ $end
$var wire 1 *" D $end
$var wire 1 1 C $end
$var reg 1 +" Q $end
$upscope $end
$upscope $end
$scope module probador $end
$var wire 1 3 active_out $end
$var wire 1 2 active_out_estr $end
$var wire 1 0 error_out $end
$var wire 1 # error_out_estr $end
$var wire 1 / idle_out $end
$var wire 1 . idle_out_estr $end
$var wire 1 - init_out $end
$var wire 1 , init_out_estr $end
$var reg 1 7 FifoEmpty $end
$var reg 1 6 FifoFull $end
$var reg 1 5 FifoRead $end
$var reg 1 4 FifoWrite $end
$var reg 1 1 clk $end
$var reg 1 ) reset $end
$var reg 1 & umbralD $end
$var reg 1 % umbralMF $end
$var reg 1 $ umbralVC $end
$upscope $end
$upscope $end
$scope module DFFSR $end
$var wire 1 ," C $end
$var wire 1 -" D $end
$var wire 1 ." R $end
$var wire 1 /" S $end
$var reg 1 0" Q $end
$upscope $end
$enddefinitions $end
#0
$dumpvars
x0"
z/"
z."
z-"
z,"
x+"
0*"
x)"
0("
x'"
0&"
x%"
0$"
0#"
x""
0!"
x~
0}
x|
0{
xz
xy
xx
xw
xv
xu
xt
xs
xr
xq
xp
xo
bz000 n
1m
xl
xk
xj
xi
xh
xg
xf
xe
xd
xc
xb
1a
1`
x_
1^
1]
0\
1[
1Z
xY
xX
xW
0V
xU
xT
1S
xR
0Q
xP
xO
xN
xM
xL
1K
xJ
xI
0H
1G
xF
0E
xD
1C
0B
1A
x@
0?
1>
0=
1<
b0xx ;
bx :
bx 9
b0 8
07
06
05
04
03
x2
01
00
0/
0.
0-
0,
b0 +
b0xx *
0)
bx (
bx '
0&
0%
0$
0#
z"
z!
$end
#4
0|
1M
1I
0J
b1 *
b1 ;
1y
0N
0O
02
0T
1h
1Y
1b
1U
0P
0L
0i
0c
0W
0D
0d
1$"
0&"
1R
1_
1j
1@
1F
1X
1k
1{
bz001 n
0}
1l
1g
1e
1f
b1 +
b1 8
0z
0w
0v
0o
0s
0r
0""
0~
0u
0p
0x
0t
0q
0S
b0 (
b0 9
0%"
0'"
0)"
b0 '
b0 :
0+"
1)
11
#8
01
#12
1&"
1}
0$"
1|
bz010 n
0{
0I
b10 *
b10 ;
0y
0M
1O
1J
1T
1,
0U
0K
0[
1W
1L
1D
1\
0X
0_
0]
0l
0^
1z
1w
1v
1o
b10 +
b10 8
1-
1$
1%
b1 '
b1 :
1%"
b1 (
b1 9
11
#16
01
#20
b10 *
b10 ;
1|
0J
1.
1N
0M
1K
0b
0W
0,
0L
0D
1c
1V
1X
1_
0j
1l
0g
0`
0m
0z
0w
0v
0o
1s
1r
1/
0-
b10 (
b10 9
0%"
b10 '
b10 :
1'"
17
11
#24
01
#28
1$"
bz011 n
1{
b11 *
b11 ;
1y
0O
0T
1U
0.
0V
1`
1m
b11 +
b11 8
0/
07
11
#32
01
#36
1&"
bz011 n
1}
1T
1J
1M
0I
0U
12
0h
0Y
0N
1P
1W
1D
1i
1b
0R
0X
0l
13
1z
1w
1v
1o
b11 (
b11 9
b11 '
b11 :
1%"
11
#40
01
#44
0&"
0$"
0}
0{
1("
bz100 n
1#"
1I
1O
1!"
0y
0<
b100 *
b100 ;
0|
0J
0P
0G
02
1Y
1H
1h
1V
1Q
0Z
1`
0m
0a
b100 +
b100 8
03
16
17
11
#48
01
#52
1=
0&"
0|
0}
0>
1("
1M
1I
0A
bz100 n
1#"
1?
1!"
1B
0N
1E
b100 *
b100 ;
0y
0<
0@
1[
1G
0D
0i
1b
0c
0V
0F
1d
1Y
0H
1R
1X
1j
0k
0Q
1l
1g
0e
0C
1Z
0z
0w
0v
0o
0s
0r
1""
1~
1u
1p
10
b100 (
b100 9
0%"
0'"
b100 '
b100 :
1)"
14
15
07
11
#56
01
#60
0("
b0 *
b0 ;
0!"
bz000 n
0#"
1>
1A
1<
0B
0?
0E
0=
1C
1m
1a
b0 +
b0 8
00
04
05
06
11
#64
01
#68
1$"
bz001 n
1{
b1 *
b1 ;
1y
0O
0T
1U
0[
0d
0W
1@
1F
1k
1e
b1 +
b1 8
0""
0~
0u
0p
b0 (
b0 9
b0 '
b0 :
0)"
11
